setup.py
gtf_to_genes/__init__.py
gtf_to_genes/default_logger.py
gtf_to_genes/dump_object.py
gtf_to_genes/gene.py
gtf_to_genes/gene_utilities.py
gtf_to_genes/gtf_to_genes_version.py
gtf_to_genes/index_gtf_files.py
gtf_to_genes/minimal_gtf_iterator.py
gtf_to_genes/random_access_file_by_sections.py
gtf_to_genes.egg-info/PKG-INFO
gtf_to_genes.egg-info/SOURCES.txt
gtf_to_genes.egg-info/dependency_links.txt
gtf_to_genes.egg-info/top_level.txt