Metadata-Version: 1.1
Name: gtf-to-genes
Version: 1.09
Summary: Fast GTF parser
Home-page: http://code.google.com/p/gtf-to-genes/
Author: Leo Goodstadt
Author-email: gtf_to_genes@llew.org.uk
License: MIT
Keywords: GTF Ensembl gene transcript parser GFF bioinformatics science
Platform: UNKNOWN
Classifier: Intended Audience :: End Users/Desktop
Classifier: Development Status :: 5 - Production/Stable
Classifier: Intended Audience :: Developers
Classifier: Intended Audience :: Science/Research
Classifier: Intended Audience :: Information Technology
Classifier: License :: OSI Approved :: MIT License
Classifier: Programming Language :: Python
Classifier: Topic :: Scientific/Engineering
Classifier: Topic :: Scientific/Engineering :: Bio-Informatics
Classifier: Environment :: Console
